pyams_file/__init__.py
pyams_file/file.py
pyams_file/image.py
pyams_file/include.py
pyams_file/property.py
pyams_file/schema.py
pyams_file/thumbnail.py
pyams_file/watermark.py
pyams_file/archive/__init__.py
pyams_file/archive/bz2.py
pyams_file/archive/gz.py
pyams_file/archive/tar.py
pyams_file/archive/zip.py
pyams_file/doctests/README.rst
pyams_file/doctests/archive.rst
pyams_file/doctests/thumbnails.rst
pyams_file/generations/__init__.py
pyams_file/generations/evolve1.py
pyams_file/generations/evolve2.py
pyams_file/generations/evolve3.py
pyams_file/interfaces/__init__.py
pyams_file/interfaces/archive.py
pyams_file/interfaces/thumbnail.py
pyams_file/locales/pyams_file.pot
pyams_file/locales/fr/LC_MESSAGES/pyams_file.mo
pyams_file/locales/fr/LC_MESSAGES/pyams_file.po
pyams_file/skin/__init__.py
pyams_file/skin/view.py
pyams_file/skin/templates/svg-render.pt
pyams_file/tests/__init__.py
pyams_file/tests/background.jpg
pyams_file/tests/icon.svg
pyams_file/tests/test_image.png
pyams_file/tests/test_image.png.bz2
pyams_file/tests/test_image.png.gz
pyams_file/tests/test_image.tar
pyams_file/tests/test_image.tar.bz2
pyams_file/tests/test_image.tar.bz2.zip
pyams_file/tests/test_image.tar.gz
pyams_file/tests/test_image.zip
pyams_file/tests/test_image_error.dwg
pyams_file/tests/test_utilsdocs.py
pyams_file/tests/test_utilsdocstrings.py
pyams_file/tests/watermark.png
pyams_file-2.4.2.dist-info/LICENSE
pyams_file-2.4.2.dist-info/METADATA
pyams_file-2.4.2.dist-info/WHEEL
pyams_file-2.4.2.dist-info/namespace_packages.txt
pyams_file-2.4.2.dist-info/top_level.txt
pyams_file-2.4.2.dist-info/RECORD
