Metadata-Version: 2.1
Name: pyams-file
Version: 2.4.2
Summary: PyAMS files management package
Home-page: https://pyams.readthedocs.io
Author: Thierry Florac
Author-email: tflorac@ulthar.net
License: ZPL
Keywords: Pyramid PyAMS
Classifier: License :: OSI Approved :: Zope Public License
Classifier: Development Status :: 4 - Beta
Classifier: Programming Language :: Python
Classifier: Framework :: Pyramid
Classifier: Topic :: Software Development :: Libraries :: Python Modules
Requires-Python: >=3.7
License-File: LICENSE
Requires-Dist: setuptools
Requires-Dist: BTrees
Requires-Dist: pillow
Requires-Dist: ZODB
Requires-Dist: persistent
Requires-Dist: pyams-i18n
Requires-Dist: pyams-site
Requires-Dist: pyams-utils
Requires-Dist: pyquery
Requires-Dist: pyramid >=2.0.0
Requires-Dist: pyramid-chameleon
Requires-Dist: python-magic
Requires-Dist: zope.annotation
Requires-Dist: zope.component
Requires-Dist: zope.container
Requires-Dist: zope.copy
Requires-Dist: zope.interface
Requires-Dist: zope.lifecycleevent
Requires-Dist: zope.location
Requires-Dist: zope.schema
Provides-Extra: test
Requires-Dist: pyams-catalog ; extra == 'test'
Requires-Dist: pyams-zmi ; extra == 'test'
